logassistant/__init__.py
logassistant/logassistant.py
logassistant-0.1.2.dist-info/LICENSE
logassistant-0.1.2.dist-info/METADATA
logassistant-0.1.2.dist-info/WHEEL
logassistant-0.1.2.dist-info/entry_points.txt
logassistant-0.1.2.dist-info/top_level.txt
logassistant-0.1.2.dist-info/RECORD
