Metadata-Version: 2.1
Name: logassistant
Version: 0.1.2
License-File: LICENSE
Requires-Dist: openai
Requires-Dist: requests
